LICENSE
README.md
setup.py
pyzjr/Z.py
pyzjr/__init__.py
pyzjr/version.py
pyzjr.egg-info/PKG-INFO
pyzjr.egg-info/SOURCES.txt
pyzjr.egg-info/dependency_links.txt
pyzjr.egg-info/requires.txt
pyzjr.egg-info/top_level.txt
pyzjr/augmentation/__init__.py
pyzjr/augmentation/transforms/__init__.py
pyzjr/augmentation/transforms/apply.py
pyzjr/augmentation/transforms/pil_and_cv.py
pyzjr/augmentation/transforms/tvision.py
pyzjr/augmentation/utils/__init__.py
pyzjr/augmentation/utils/adjust_color.py
pyzjr/augmentation/utils/binary.py
pyzjr/augmentation/utils/blur.py
pyzjr/augmentation/utils/contour.py
pyzjr/augmentation/utils/dt.py
pyzjr/augmentation/utils/geometric.py
pyzjr/augmentation/utils/noise.py
pyzjr/augmentation/utils/skeleton_extraction.py
pyzjr/data/__init__.py
pyzjr/data/loaders.py
pyzjr/data/datasets/__init__.py
pyzjr/data/datasets/custom_dataset.py
pyzjr/data/datasets/image_classifier_dataset.py
pyzjr/data/datasets/pascal_voc.py
pyzjr/data/utils/__init__.py
pyzjr/data/utils/clean.py
pyzjr/data/utils/data_utils.py
pyzjr/data/utils/file.py
pyzjr/data/utils/folder.py
pyzjr/data/utils/listfun.py
pyzjr/data/utils/path.py
pyzjr/data/utils/script.py
pyzjr/data/utils/tuplefun.py
pyzjr/data/utils/txtfun.py
pyzjr/measure/__init__.py
pyzjr/measure/quality_eval.py
pyzjr/measure/fissure/__init__.py
pyzjr/measure/fissure/crack.py
pyzjr/nn/__init__.py
pyzjr/nn/callbacks.py
pyzjr/nn/devices.py
pyzjr/nn/save_pth.py
pyzjr/nn/strategy.py
pyzjr/nn/tools.py
pyzjr/nn/losses/__init__.py
pyzjr/nn/losses/loss_function.py
pyzjr/nn/losses/loss_utils.py
pyzjr/nn/metrics/__init__.py
pyzjr/nn/metrics/classification.py
pyzjr/nn/metrics/infer_testset.py
pyzjr/nn/metrics/segmentation.py
pyzjr/nn/metrics/utils.py
pyzjr/nn/models/__init__.py
pyzjr/nn/models/_utils.py
pyzjr/nn/models/atten/__init__.py
pyzjr/nn/models/atten/bam.py
pyzjr/nn/models/atten/cbam.py
pyzjr/nn/models/atten/cot.py
pyzjr/nn/models/atten/se.py
pyzjr/nn/models/bricks/__init__.py
pyzjr/nn/models/bricks/conbine.py
pyzjr/nn/models/bricks/conv_norm.py
pyzjr/nn/models/bricks/drop.py
pyzjr/nn/models/bricks/initer.py
pyzjr/nn/models/bricks/pool.py
pyzjr/nn/optim/__init__.py
