Metadata-Version: 2.1
Name: pyzjr
Version: 1.4.20
Summary:  A computer vision library that supports Win, packaged with patches for visual libraries such as                 Opencv, matplotlib, and image. In the future, Pytorch will also be supported, all of which are personal (Auorui)                 engineering code experience. 
Home-page: https://github.com/Auorui/pyzjr
Author: Auorui
Author-email: zjricetea@gmail.com
License: MIT
Keywords: python,computer vision,pyzjr,windows
Classifier: Development Status :: 1 - Planning
Classifier: Intended Audience :: Developers
Classifier: Programming Language :: Python :: 3
Classifier: Operating System :: Microsoft :: Windows
License-File: LICENSE
Requires-Dist: requests
Requires-Dist: tqdm
Requires-Dist: seaborn
Requires-Dist: opencv-python
Requires-Dist: scikit-learn
Requires-Dist: scikit-image
Requires-Dist: torch
Requires-Dist: thop
Requires-Dist: argparse
Requires-Dist: pyyaml
Requires-Dist: tensorboard
Requires-Dist: psutil
Requires-Dist: torchvision
